LICENSE
MANIFEST.in
README.rst
setup.py
django_magic_db_router/__init__.py
django_magic_db_router/router.py
django_magic_db_router.egg-info/PKG-INFO
django_magic_db_router.egg-info/SOURCES.txt
django_magic_db_router.egg-info/dependency_links.txt
django_magic_db_router.egg-info/top_level.txt
docs/todo.txt