Metadata-Version: 1.1
Name: django-magic-db-router
Version: 0.1
Summary: Dynamic database router
Home-page: https://www.cloudjetkpi.com/
Author: Thoi Ngoc Quoc Duan
Author-email: duan@cjs.vn/quocduan@gmail.com
License: CLOUDJET SOLUTIONS License
Platform: UNKNOWN
Classifier: Environment :: Web Environment
Classifier: Framework :: Django
Classifier: Framework :: Django :: 1.9
Classifier: Intended Audience :: Developers
Classifier: License :: OSI Approved :: BSD License
Classifier: Operating System :: OS Independent
Classifier: Programming Language :: Python
Classifier: Programming Language :: Python :: 2.7
Classifier: Topic :: Internet :: WWW/HTTP
Classifier: Topic :: Internet :: WWW/HTTP :: Dynamic Content
